{
  "authorial": {
    "description": "Authorial voice/style probes",
    "labels": {"angry":0,"anxious":1,"awed":2,"bitter":3,"conflicted":4,"despairing":5,"detached":6,"hurried":7,"joyful":8,"passionate":9,"perfunctory":10,"playful":11,"sorrowful":12,"tender":13,"unknown":14}
  },
  "authorial_docdenoised": {
    "description": "Authorial voice (document-denoised)",
    "labels": {"angry":0,"anxious":1,"awed":2,"bitter":3,"conflicted":4,"despairing":5,"detached":6,"hurried":7,"joyful":8,"passionate":9,"perfunctory":10,"playful":11,"sorrowful":12,"tender":13,"unknown":14}
  },
  "axis275_filtered": {
    "description": "275-axis behavioral decomposition (filtered)",
    "labels": {"pc1":0,"pc2":1,"pc3":2,"pc4":3,"pc5":4,"contrast":5}
  },
  "axis_role": {
    "description": "Role behavior axes",
    "labels": {"pc1":0,"pc2":1,"pc3":2,"pc4":3,"pc5":4}
  },
  "deflection": {
    "description": "Emotion deflection/concealment",
    "labels": {"afraid":0,"angry":1,"desperate":2,"guilty":3,"nervous":4,"sad":5,"hiddenness":6}
  },
  "desires": {
    "description": "Desire/contentment axis",
    "labels": {"wanting":0,"content":1}
  },
  "emotion": {
    "description": "170 emotion probes",
    "labels": {"afraid":0,"alarmed":1,"alert":2,"amazed":3,"amused":4,"angry":5,"annoyed":6,"anxious":7,"aroused":8,"ashamed":9,"astonished":10,"at ease":11,"awestruck":12,"bewildered":13,"bitter":14,"blissful":15,"bored":16,"brooding":17,"calm":18,"cheerful":19,"compassionate":20,"contemptuous":21,"content":22,"defiant":23,"delighted":24,"dependent":25,"depressed":26,"desperate":27,"disdainful":28,"disgusted":29,"disoriented":30,"dispirited":31,"distressed":32,"disturbed":33,"docile":34,"droopy":35,"dumbstruck":36,"eager":37,"ecstatic":38,"elated":39,"embarrassed":40,"empathetic":41,"energized":42,"enraged":43,"enthusiastic":44,"envious":45,"euphoric":46,"exasperated":47,"excited":48,"exuberant":49,"frightened":50,"frustrated":51,"fulfilled":52,"furious":53,"gloomy":54,"grateful":55,"greedy":56,"grief-stricken":57,"grumpy":58,"guilty":59,"happy":60,"hateful":61,"heartbroken":62,"hope":63,"hopeful":64,"horrified":65,"hostile":66,"humiliated":67,"hurt":68,"hysterical":69,"impatient":70,"indifferent":71,"indignant":72,"infatuated":73,"inspired":74,"insulted":75,"invigorated":76,"irate":77,"irritated":78,"jealous":79,"joyful":80,"jubilant":81,"kind":82,"lazy":83,"listless":84,"lonely":85,"loving":86,"mad":87,"melancholy":88,"miserable":89,"mortified":90,"mystified":91,"nervous":92,"nostalgic":93,"obstinate":94,"offended":95,"on edge":96,"optimistic":97,"outraged":98,"overwhelmed":99,"panicked":100,"paranoid":101,"patient":102,"peaceful":103,"perplexed":104,"playful":105,"pleased":106,"proud":107,"puzzled":108,"rattled":109,"reflective":110,"refreshed":111,"regretful":112,"rejuvenated":113,"relaxed":114,"relieved":115,"remorseful":116,"resentful":117,"resigned":118,"restless":119,"sad":120,"safe":121,"satisfied":122,"scared":123,"scornful":124,"self-confident":125,"self-conscious":126,"self-critical":127,"sensitive":128,"sentimental":129,"serene":130,"shaken":131,"shocked":132,"skeptical":133,"sleepy":134,"sluggish":135,"smug":136,"sorry":137,"spiteful":138,"stimulated":139,"stressed":140,"stubborn":141,"stuck":142,"sullen":143,"surprised":144,"suspicious":145,"sympathetic":146,"tense":147,"terrified":148,"thankful":149,"thrilled":150,"tired":151,"tormented":152,"trapped":153,"triumphant":154,"troubled":155,"uneasy":156,"unhappy":157,"unnerved":158,"unsettled":159,"upset":160,"valiant":161,"vengeful":162,"vibrant":163,"vigilant":164,"vindictive":165,"vulnerable":166,"weary":167,"worn out":168,"worried":169,"worthless":170}
  },
  "fears": {
    "description": "Threat/safety axis",
    "labels": {"threatened":0,"safe":1}
  },
  "genre": {
    "description": "Genre/register probes",
    "labels": {"dialogue":0,"fairy_tale":1,"fiction_genre":2,"fiction_literary":3,"journalism":4,"legal":5,"nonfiction_academic":6,"nonfiction_essay":7,"poetry_lyric":8,"poetry_narrative":9,"religious":10,"satire":11,"stream_of_consciousness":12,"technical":13}
  },
  "narrative_depth": {
    "description": "Narrative depth components",
    "labels": {"depth":0,"referentiality":1,"evidentiality":2,"agency":3,"desires":4,"fears":5}
  },
  "sae_hubs": {
    "description": "SAE-derived hub features",
    "labels": {"broadcast_f12454":0,"broadcast_f38889":1,"broadcast_f7631":2,"broadcast_f13797":3,"broadcast_f96733":4,"backbone_f26292":5,"backbone_f26293":6,"hub_f67160":7,"hub_f5282":8,"hub_f56151":9}
  }
}
